leukeleu_django_gdpr/__init__.py
leukeleu_django_gdpr/anonymize.py
leukeleu_django_gdpr/apps.py
leukeleu_django_gdpr/checks.py
leukeleu_django_gdpr/gdpr.py
leukeleu_django_gdpr/management/__init__.py
leukeleu_django_gdpr/management/commands/__init__.py
leukeleu_django_gdpr/management/commands/anonymize.py
leukeleu_django_gdpr/management/commands/gdpr.py
leukeleu_django_gdpr-1.6.2.dist-info/licenses/LICENSE
leukeleu_django_gdpr-1.6.2.dist-info/WHEEL
leukeleu_django_gdpr-1.6.2.dist-info/METADATA
leukeleu_django_gdpr-1.6.2.dist-info/RECORD
