Metadata-Version: 2.4
Name: leukeleu_django_gdpr
Version: 1.6.2
Summary: leukeleu-django-gdpr is a tool to generate GDPR documentation based on the project's models.
Author: Wouter de Vries
Author-email: Wouter de Vries <wdevries@leukeleu.nl>
License-Expression: MIT
License-File: LICENSE
Classifier: License :: OSI Approved :: MIT License
Classifier: Development Status :: 5 - Production/Stable
Classifier: Framework :: Django
Classifier: Intended Audience :: Developers
Classifier: Programming Language :: Python :: 3
Requires-Dist: django>=4.2,<6
Requires-Dist: pyyaml
Requires-Dist: faker ; extra == 'anonymize'
Requires-Python: >=3.10
Project-URL: Issues, https://github.com/leukeleu/leukeleu-django-gdpr/issues
Project-URL: Releasenotes, https://github.com/leukeleu/leukeleu-django-gdpr/releases
Project-URL: Repository, https://github.com/leukeleu/leukeleu-django-gdpr/
Provides-Extra: anonymize
